BaiduImagesDownload/__init__.py
BaiduImagesDownload-2.0.0.dist-info/LICENSE
BaiduImagesDownload-2.0.0.dist-info/METADATA
BaiduImagesDownload-2.0.0.dist-info/WHEEL
BaiduImagesDownload-2.0.0.dist-info/top_level.txt
BaiduImagesDownload-2.0.0.dist-info/RECORD
