Metadata-Version: 2.1
Name: BaiduImagesDownload
Version: 2.0.0
Summary: download image from Baidu Image
Home-page: https://github.com/YXL76/BaiduImagesDownload
Author: YXL
Author-email: chenxin.lan.76@gmail.com
License: MIT
Platform: UNKNOWN
Classifier: License :: OSI Approved :: MIT License
Classifier: Programming Language :: Python :: 3
Classifier: Programming Language :: Python :: 3.8
Requires-Dist: aiodns (==2.0.0)
Requires-Dist: aiohttp (==3.7.3)
Requires-Dist: cchardet (==2.1.7)
Requires-Dist: tqdm (==4.55.1)
